sanic_ext/__init__.py
sanic_ext_base-0.1.0.dist-info/LICENSE
sanic_ext_base-0.1.0.dist-info/METADATA
sanic_ext_base-0.1.0.dist-info/WHEEL
sanic_ext_base-0.1.0.dist-info/top_level.txt
sanic_ext_base-0.1.0.dist-info/RECORD
