Metadata-Version: 2.1
Name: sanic-ext-base
Version: 0.1.0
Summary: Flask-like extension support for Sanic framework
Home-page: https://github.com/openwhalereef/sanic-ext-base
Author: Open Whalereef
Author-email: open@whalereef.com
License: BSD
Platform: any
Classifier: Environment :: Web Environment
Classifier: License :: OSI Approved :: BSD License
Classifier: Intended Audience :: Developers
Classifier: Operating System :: OS Independent
Classifier: Programming Language :: Python
Classifier: Programming Language :: Python :: 3
Classifier: Programming Language :: Python :: 3.5
Classifier: Programming Language :: Python :: 3.6
Classifier: Programming Language :: Python :: 3.7
Classifier: Programming Language :: Python :: Implementation :: CPython
Classifier: Topic :: Software Development :: Libraries :: Python Modules
